_pydart2_api.cpython-35m-x86_64-linux-gnu.so
.libs_pydart2_api/libLinearMath-f238c44c.so.2.83
.libs_pydart2_api/libicuuc-6d414df8.so.55.1
.libs_pydart2_api/libdart-external-odelcpsolver-a30be6ec.so.6.2.1
.libs_pydart2_api/libBulletCollision-db660f94.so.2.83
.libs_pydart2_api/libdart-gui-c265cca2.so.6.2.1
.libs_pydart2_api/libfcl-20b8dd1c.so.0
.libs_pydart2_api/libboost_system-c115ab76.so.1.58.0
.libs_pydart2_api/libtinyxml2-9142dc5b.so.2.2.0
.libs_pydart2_api/libdart-utils-20879e6f.so.6.2.1
.libs_pydart2_api/libdart-collision-ode-5c73f9c2.so.6.2.1
.libs_pydart2_api/libdart-external-lodepng-3abedaa6.so.6.2.1
.libs_pydart2_api/libz-1ec5f3c6.so.1.2.8
.libs_pydart2_api/libode-1beba16d.so.4.1.0
.libs_pydart2_api/libicudata-5c0544e9.so.55.1
.libs_pydart2_api/libtinyxml-17e624c0.so.2.6.2
.libs_pydart2_api/libccd-baccb67e.so.2.0
.libs_pydart2_api/libminizip-653805ca.so.1.0.0
.libs_pydart2_api/libicui18n-46fc72d1.so.55.1
.libs_pydart2_api/libXi-9314c25f.so.6.1.0
.libs_pydart2_api/libassimp-28a76b54.so.3.2.0
.libs_pydart2_api/libconsole_bridge-2b24a2f9.so.0.2
.libs_pydart2_api/libdart-utils-urdf-74dab856.so.6.2.1
.libs_pydart2_api/liburdfdom_model-7e647fee.so.0.4
.libs_pydart2_api/libGLU-d9039f4a.so.1.3.1
.libs_pydart2_api/libboost_regex-51ef8a73.so.1.58.0
.libs_pydart2_api/libdart-45a951db.so.6.2.1
.libs_pydart2_api/libXxf86vm-f410f7be.so.1.0.0
.libs_pydart2_api/libdart-collision-bullet-d98c7cee.so.6.2.1
.libs_pydart2_api/libglut-94134954.so.3.9.0
pydart2/contact.py
pydart2/skel_vector.py
pydart2/shapenode.py
pydart2/bodynode.py
pydart2/collision_result.py
pydart2/__init__.py
pydart2/shape.py
pydart2/pydart2_api.py
pydart2/constraints.py
pydart2/world.py
pydart2/dof.py
pydart2/recording.py
pydart2/joint.py
pydart2/skeleton.py
pydart2/marker.py
pydart2/muscle/model_geyer_2010.py
pydart2/muscle/tendon_unit.py
pydart2/muscle/__init__.py
pydart2/muscle/route.py
pydart2/muscle/skeleton.py
pydart2/utils/jsonpickle.py
pydart2-0.7.4.dist-info/WHEEL
pydart2-0.7.4.dist-info/metadata.json
pydart2-0.7.4.dist-info/DESCRIPTION.rst
pydart2-0.7.4.dist-info/METADATA
pydart2-0.7.4.dist-info/top_level.txt
pydart2-0.7.4.dist-info/RECORD
