Metadata-Version: 2.0
Name: pydart2
Version: 0.7.4
Summary: Python Interface for DART Simulator
Home-page: https://github.com/sehoonha/pydart2
Author: Sehoon Ha
Author-email: sehoon.ha@gmail.com
License: BSD
Keywords: physics,robotics,simulation
Platform: UNKNOWN
Classifier: Development Status :: 2 - Pre-Alpha
Classifier: License :: OSI Approved :: BSD License
Classifier: Operating System :: POSIX :: Linux
Classifier: Intended Audience :: Science/Research
Classifier: Programming Language :: Python
Classifier: Programming Language :: Python :: 2.7
Classifier: Programming Language :: Python :: 3.5
Classifier: Topic :: Games/Entertainment :: Simulation
Requires-Dist: PyOpenGL
Requires-Dist: colorama
Requires-Dist: future
Requires-Dist: numpy
Requires-Dist: six
